pytest_durations/__init__.py
pytest_durations/helpers.py
pytest_durations/measure.py
pytest_durations/options.py
pytest_durations/plugin.py
pytest_durations/reporting.py
pytest_durations/ticker.py
pytest_durations/types.py
pytest_durations/typing.pyi
pytest_durations/xdist.py
pytest_durations-1.6.1.dist-info/LICENSE
pytest_durations-1.6.1.dist-info/METADATA
pytest_durations-1.6.1.dist-info/WHEEL
pytest_durations-1.6.1.dist-info/entry_points.txt
pytest_durations-1.6.1.dist-info/RECORD
