Metadata-Version: 2.3
Name: pytest-durations
Version: 1.6.1
Summary: Pytest plugin reporting fixtures and test functions execution time.
License: MIT
Author: Oleg Blednov
Author-email: oleg.codev@gmail.com
Requires-Python: >=3.9,<4.0
Classifier: Development Status :: 5 - Production/Stable
Classifier: Framework :: Pytest
Classifier: Intended Audience :: Developers
Classifier: License :: OSI Approved :: MIT License
Classifier: Operating System :: OS Independent
Classifier: Programming Language :: Python :: 3
Classifier: Programming Language :: Python :: 3.9
Classifier: Programming Language :: Python :: 3.10
Classifier: Programming Language :: Python :: 3.11
Classifier: Programming Language :: Python :: 3.12
Classifier: Programming Language :: Python :: 3.13
Classifier: Topic :: Software Development :: Testing
Requires-Dist: pytest (>=4.6)
Project-URL: Homepage, https://github.com/blake-r/pytest-durations
Project-URL: Repository, https://github.com/blake-r/pytest-durations
